valr/__init__.py
valr/account.py
valr/client.py
valr/exchange_buy_sell.py
valr/market_data.py
valr/pay.py
valr/public.py
valr/session.py
valr/simple_buy_sell.py
valr/wallet.py
valr_simple_client-0.0.2.dist-info/LICENSE
valr_simple_client-0.0.2.dist-info/METADATA
valr_simple_client-0.0.2.dist-info/WHEEL
valr_simple_client-0.0.2.dist-info/top_level.txt
valr_simple_client-0.0.2.dist-info/RECORD
