Metadata-Version: 2.1
Name: valr-simple-client
Version: 0.0.2
Summary: VALR API Client
Home-page: https://github.com/Moon-developer/Valr-simple-client
Author: Marco Fernandes
License: MIT
Keywords: python,package,valr,crypto,api,rest,client
Platform: UNKNOWN
Classifier: Development Status :: 1 - Planning
Classifier: Intended Audience :: Developers
Classifier: License :: OSI Approved :: MIT License
Classifier: Programming Language :: Python :: 3.8
Classifier: Programming Language :: Python :: 3.9
Classifier: Programming Language :: Python :: 3.10
Classifier: Operating System :: POSIX :: Linux
Classifier: Topic :: Software Development
Requires-Python: >=3.8
License-File: LICENSE
Requires-Dist: requests
Requires-Dist: python-dotenv
